apigatewayauth/__init__.py
apigatewayauth/apps.py
apigatewayauth/authentication.py
apigatewayauth/id_token.py
apigatewayauth/patch.py
apigatewayauth/permissions.py
apigatewayauth/permissions_spec.py
apigatewayauth/tests/__init__.py
apigatewayauth/tests/mocks/__init__.py
apigatewayauth/tests/mocks/apps.py
apigatewayauth/tests/mocks/migrations/0001_initial.py
apigatewayauth/tests/mocks/migrations/__init__.py
apigatewayauth/tests/mocks/mock_ibis.py
apigatewayauth/tests/mocks/models.py
apigatewayauth/tests/mocks/permissions_spec.py
apigatewayauth/tests/mocks/permissions_spec.yml
apigatewayauth/tests/mocks/test_model_migrations.py
apigatewayauth/tests/test_apigateway_auth.py
apigatewayauth/tests/test_patch.py
apigatewayauth/tests/test_permissions.py
apigatewayauth/tests/test_permissions_spec.py
apigatewayauth/tests/test_schema.py
apigatewayauth/user.py
django_ucam_apigatewayauth-1.0.2.dist-info/METADATA
django_ucam_apigatewayauth-1.0.2.dist-info/WHEEL
django_ucam_apigatewayauth-1.0.2.dist-info/RECORD
