Metadata-Version: 2.4
Name: django-ucam-apigatewayauth
Version: 1.0.2
Summary: A Django module allow auth based on the headers passed from the API Gateway
License: MIT
Author: DevOps Division, University Information Services, University of Cambridge
Author-email: devops@uis.cam.ac.uk
Requires-Python: >=3.10,<4.0
Classifier: Development Status :: 3 - Alpha
Classifier: Environment :: Web Environment
Classifier: Framework :: Django
Classifier: Intended Audience :: Developers
Classifier: License :: OSI Approved :: MIT License
Classifier: Operating System :: OS Independent
Classifier: Programming Language :: Python
Classifier: Programming Language :: Python :: 3
Classifier: Programming Language :: Python :: 3.10
Classifier: Programming Language :: Python :: 3.11
Classifier: Programming Language :: Python :: 3.12
Classifier: Programming Language :: Python :: 3.13
Classifier: Programming Language :: Python :: 3.14
Requires-Dist: cachecontrol (>=0.14.0,<0.15.0)
Requires-Dist: django (>=3.2.7,<6.0.0)
Requires-Dist: django-ucamlookup (>=3.1.0,<3.2.0)
Requires-Dist: djangorestframework (>=3.14.0,<4.0.0)
Requires-Dist: drf-spectacular (>=0.29.0,<0.30.0)
Requires-Dist: geddit (>=2.0.0,<3.0.0)
Requires-Dist: google-auth (>=2.23.2,<3.0.0)
Requires-Dist: legacy-cgi (>=2.6.0,<3.0.0) ; python_full_version > "3.12.0"
Requires-Dist: pyyaml (>=6.0.1,<7.0.0)
Requires-Dist: ucam-identitylib (>=3.0.0,<4.0.0)
